{
  "version": "1.0.0",
  "purpose": "HIPAA-compliant audit trail for credential rotations",
  "retentionPeriod": "7 years (HIPAA requirement)",
  "entries": [
    {
      "timestamp": "2025-01-15T00:00:00.000Z",
      "credentialId": "gcp-service-account-001",
      "credentialName": "GCP Service Account - ssd-automation-service-account",
      "action": "rotation_completed",
      "performedBy": "system_admin",
      "details": {
        "previousDueDate": "2024-01-15",
        "newDueDate": "2026-01-15",
        "schedule": "annual",
        "reason": "Initial setup"
      }
    },
    {
      "timestamp": "2025-01-15T00:00:00.000Z",
      "credentialId": "gcs-service-account-001",
      "credentialName": "GCS Backup Service Account",
      "action": "rotation_completed",
      "performedBy": "system_admin",
      "details": {
        "previousDueDate": "2024-01-15",
        "newDueDate": "2026-01-15",
        "schedule": "annual",
        "reason": "Initial setup for GCS backup system"
      }
    }
  ]
}
